package/__init__.py
package/app.py
package/auth.py
package/config.py
package/diagnose.py
package/git_utils.py
package/review.py
package/server.py
package/test_review.py
package/token_utils.py
package/user.py
package/utils.py
package/version.py
package/tests/__init__.py
package/tests/test_auth.py
package/tests/test_git_utils.py
package/tests/test_review.py
prist/__init__.py
prist/review.py
prist/setup.py
prist/test_review.py
codara-2.0.6.dist-info/METADATA
codara-2.0.6.dist-info/WHEEL
codara-2.0.6.dist-info/entry_points.txt
codara-2.0.6.dist-info/top_level.txt
codara-2.0.6.dist-info/RECORD
