Metadata-Version: 2.1
Name: codara
Version: 2.0.6
Summary: AI Code Review Automation Tool
Requires-Dist: annotated-types==0.6.0
Requires-Dist: anyio==3.7.1
Requires-Dist: blinker==1.7.0
Requires-Dist: certifi==2023.11.17
Requires-Dist: cffi==1.16.0
Requires-Dist: charset-normalizer==3.3.2
Requires-Dist: click==8.1.7
Requires-Dist: cryptography==41.0.7
Requires-Dist: distro==1.8.0
Requires-Dist: Flask==3.0.0
Requires-Dist: h11==0.14.0
Requires-Dist: httpcore==1.0.2
Requires-Dist: httpx==0.25.2
Requires-Dist: idna==3.6
Requires-Dist: iniconfig==2.0.0
Requires-Dist: itsdangerous==2.1.2
Requires-Dist: Jinja2==3.1.2
Requires-Dist: MarkupSafe==2.1.3
Requires-Dist: openai==1.3.7
Requires-Dist: packaging==23.2
Requires-Dist: pluggy==1.3.0
Requires-Dist: pycparser==2.21
Requires-Dist: pydantic==2.5.2
Requires-Dist: pydantic-core==2.14.5
Requires-Dist: PyJWT==2.8.0
Requires-Dist: pytest==7.4.3
Requires-Dist: requests==2.31.0
Requires-Dist: sniffio==1.3.0
Requires-Dist: tqdm==4.66.1
Requires-Dist: typing-extensions==4.8.0
Requires-Dist: urllib3==2.1.0
Requires-Dist: Werkzeug==3.0.1
Requires-Dist: gunicorn==21.2.0
Requires-Dist: tornado==6.4
